{
    "Version": "1.1",
    "Data": {
        "Source": "e:\\00.project\\00.studyunreal\\1.server\\myproject\\source\\myproject\\myproject.cpp",
        "ProvidedModule": "",
        "PCH": "e:\\00.project\\00.studyunreal\\1.server\\myproject\\intermediate\\build\\win64\\myprojecteditor\\development\\engine\\sharedpch.engine.shadowerrors.h.pch",
        "Includes": [
            "e:\\00.project\\00.studyunreal\\1.server\\myproject\\intermediate\\build\\win64\\unrealeditor\\development\\myproject\\definitions.myproject.h",
            "e:\\00.project\\00.studyunreal\\1.server\\myproject\\source\\myproject\\myproject.h"
        ],
        "ImportedModules": [],
        "ImportedHeaderUnits": []
    }
}